{
	"animations": [
		{
			"offsets": [
				-5,
				0
			],
			"loop": false,
			"fps": 30,
			"anim": "idle",
			"indices": [],
			"name": "Idle0"
		},
		{
			"offsets": [
				-25,
				0
			],
			"loop": false,
			"fps": 30,
			"anim": "idle-alt",
			"indices": [],
			"name": "IdleAlt0"
		},
		{
			"loop": false,
			"offsets": [
				-4,
				0
			],
			"anim": "singUP",
			"fps": 30,
			"name": "Up0",
			"indices": []
		},
		{
			"loop": false,
			"offsets": [
				42,
				0
			],
			"anim": "singUP-alt",
			"fps": 30,
			"name": "UpAlt0",
			"indices": []
		},
		{
			"loop": false,
			"offsets": [
				-5,
				0
			],
			"anim": "singLEFT",
			"fps": 30,
			"name": "Left0",
			"indices": []
		},
		{
			"loop": false,
			"offsets": [
				-27,
				-4
			],
			"anim": "singLEFT-alt",
			"fps": 30,
			"name": "LeftAlt0",
			"indices": []
		},
		{
			"loop": false,
			"offsets": [
				-6,
				-2
			],
			"anim": "singRIGHT",
			"fps": 30,
			"name": "Right0",
			"indices": []
		},
		{
			"loop": false,
			"offsets": [
				-25,
				-3
			],
			"anim": "singRIGHT-alt",
			"fps": 30,
			"name": "RightAlt0",
			"indices": []
		},
		{
			"offsets": [
				-19,
				-2
			],
			"loop": false,
			"fps": 30,
			"anim": "singDOWN",
			"indices": [],
			"name": "Down0"
		},
		{
			"offsets": [
				-39,
				-5
			],
			"loop": false,
			"fps": 30,
			"anim": "singDOWN-alt",
			"indices": [],
			"name": "DownAlt0"
		},
		{
			"loop": false,
			"offsets": [
				-5,
				0
			],
			"anim": "Statue",
			"fps": 30,
			"name": "statuemove",
			"indices": []
		},
		{
			"offsets": [
				-5,
				0
			],
			"loop": true,
			"fps": 30,
			"anim": "stay",
			"indices": [],
			"name": "statuemove0029"
		}
	],
	"vocals_file": "",
	"no_antialiasing": false,
	"image": "characters/MoNormal",
	"position": [
		-80,
		-55
	],
	"healthicon": "mo",
	"flip_x": false,
	"healthbar_colors": [
		108,
		17,
		16
	],
	"camera_position": [
		200,
		60
	],
	"sing_duration": 5,
	"scale": 1,
	"_editor_isPlayer": false
}